{"status": 1, "month": 5, "data": [{"factory": "总公司", "id": "DMY125后", "name": "托架（发釜川）", "first": 0, "now": 0, "in": 0, "out": 0}, {"factory": "总公司", "id": "DMY125后", "name": "弹簧座（发釜川）", "first": 0, "now": 0, "in": 0, "out": 0}, {"factory": "总公司", "id": "CB125T后", "name": "弹簧座（发釜川）", "first": 0, "now": 0, "in": 0, "out": 0}, {"factory": "总公司", "id": "GFML后", "name": "托架", "first": 0, "now": 0, "in": 0, "out": 0}, {"factory": "总公司", "id": "CN70后", "name": "托架（发釜川）", "first": 0, "now": 0, "in": 0, "out": 0}, {"factory": "总公司", "id": "WH125T后", "name": "托架（发釜川）", "first": 0, "now": 0, "in": 0, "out": 0}, {"factory": "总公司", "id": "AG50后", "name": "阻尼帽（发釜川）", "first": 0, "now": 0, "in": 0, "out": 0}, {"factory": "骏亿", "id": "CQ102后", "name": "阻尼帽（发釜川）", "first": 0, "now": 0, "in": 0, "out": 0}, {"factory": "总公司", "id": "C002后", "name": "连接环", "first": 0, "now": 0, "in": 0, "out": 0}, {"factory": "总公司", "id": "CN70后", "name": "连接环", "first": 0, "now": 0, "in": 0, "out": 0}, {"factory": "总公司", "id": "GN125后", "name": "连接环", "first": 0, "now": 0, "in": 0, "out": 0}, {"factory": "", "id": "HS50DB后", "name": "连接环（发利源）", "first": 0, "now": 0, "in": 0, "out": 0}, {"factory": "总公司", "id": "JH125后", "name": "连接环(发釜川）", "first": 0, "now": 0, "in": 0, "out": 0}, {"factory": "总公司", "id": "YDX后", "name": "连接环(发釜川）", "first": 0, "now": 0, "in": 0, "out": 0}, {"factory": "总公司", "id": "A6后", "name": "弹簧座(发釜川）", "first": 0, "now": 0, "in": 0, "out": 0}, {"factory": "总公司", "id": "LX125-5", "name": "垫圈A后", "first": 199, "now": 199, "in": 0, "out": 0}, {"factory": "总公司", "id": "LX125-5", "name": "垫圈B后", "first": 199, "now": 199, "in": 0, "out": 0}, {"factory": "渝北特", "id": "后减震油", "name": "减震油（170kg）", "first": 0, "now": 0, "in": 0, "out": 0}, {"factory": "渝北特", "id": "前减震油", "name": "减震油（170kg）", "first": 0, "now": 0, "in": 0, "out": 0}, {"factory": "总公司", "id": "9.7*1.9", "name": "O型圈", "first": 22500, "now": 22500, "in": 0, "out": 0}, {"factory": "总公司", "id": "7.7*1.9", "name": "O型圈", "first": 13000, "now": 13000, "in": 0, "out": 0}, {"factory": "青岛睿智森", "id": "CN381", "name": "O型圈", "first": 0, "now": 0, "in": 0, "out": 0}, {"factory": "方圆", "id": "CB125T后", "name": "阀片C", "first": 10000, "now": 10000, "in": 0, "out": 0}, {"factory": "总公司", "id": "CQ036后", "name": "阀片A", "first": 6000, "now": 6000, "in": 0, "out": 0}, {"factory": "方圆", "id": "CQ065M后", "name": "阀片", "first": 0, "now": 0, "in": 0, "out": 0}, {"factory": "方圆", "id": "CY80后", "name": "阀片", "first": 30000, "now": 30000, "in": 0, "out": 0}, {"factory": "方圆", "id": "CN221后", "name": "底阀片B", "first": 5000, "now": 5000, "in": 0, "out": 0}, {"factory": "方圆", "id": "CN221后", "name": "底阀片F", "first": 1000, "now": 1000, "in": 0, "out": 0}, {"factory": "方圆", "id": "CN360Q", "name": "阀片B", "first": 5962, "now": 5962, "in": 0, "out": 0}, {"factory": "方圆", "id": "CN360Q", "name": "阀片C", "first": 2996, "now": 2996, "in": 0, "out": 0}, {"factory": "总公司", "id": "GFML后", "name": "阀片B", "first": 40000, "now": 40000, "in": 0, "out": 0}, {"factory": "方圆", "id": "GN125后", "name": "阀片A", "first": 55000, "now": 55000, "in": 0, "out": 0}, {"factory": "方圆", "id": "GN125后", "name": "阀片B", "first": 130000, "now": 130000, "in": 0, "out": 0}, {"factory": "方圆", "id": "GN125后", "name": "底阀片", "first": 2000, "now": 2000, "in": 0, "out": 0}, {"factory": "方圆", "id": "JH125后", "name": "阀片A", "first": 70000, "now": 70000, "in": 0, "out": 0}, {"factory": "方圆", "id": "JH125后", "name": "阀片B", "first": 0, "now": 0, "in": 0, "out": 0}, {"factory": "方圆", "id": "JH125后", "name": "阀片C", "first": 15000, "now": 15000, "in": 0, "out": 0}, {"factory": "", "id": "JH138后", "name": "阀片A", "first": 1960, "now": 1960, "in": 0, "out": 0}, {"factory": "方圆", "id": "JH150TA后", "name": "阀片B", "first": 4000, "now": 4000, "in": 0, "out": 0}, {"factory": "方圆", "id": "JH419后", "name": "阀片B", "first": 10000, "now": 10000, "in": 0, "out": 0}, {"factory": "方圆", "id": "JH426后", "name": "阀片A", "first": 7000, "now": 7000, "in": 0, "out": 0}, {"factory": "方圆", "id": "JH426后", "name": "阀片B", "first": 7000, "now": 7000, "in": 0, "out": 0}, {"factory": "方圆", "id": "JH426后", "name": "阀片C", "first": 7000, "now": 7000, "in": 0, "out": 0}, {"factory": "方圆", "id": "JH426后", "name": "阀片D", "first": 7000, "now": 7000, "in": 0, "out": 0}, {"factory": "方圆", "id": "JH70后", "name": "阀片", "first": 3000, "now": 3000, "in": 0, "out": 0}, {"factory": "方圆", "id": "KSBIS后", "name": "阀片B", "first": 2000, "now": 2000, "in": 0, "out": 0}, {"factory": "方圆", "id": "KTTA后", "name": "底阀片A", "first": 999, "now": 999, "in": 0, "out": 0}, {"factory": "方圆", "id": "KTTA后", "name": "阀片D", "first": 999, "now": 999, "in": 0, "out": 0}, {"factory": "方圆", "id": "LX125-5后", "name": "阀片E", "first": 999, "now": 999, "in": 0, "out": 0}, {"factory": "方圆", "id": "LX125-5后", "name": "阀片I", "first": 999, "now": 999, "in": 0, "out": 0}, {"factory": "方圆", "id": "LF100ST后", "name": "阀片A", "first": 5000, "now": 5000, "in": 0, "out": 0}, {"factory": "方圆", "id": "MM100后", "name": "阀片A", "first": 10000, "now": 10000, "in": 0, "out": 0}, {"factory": "方圆", "id": "MM100后", "name": "阀片B", "first": 13000, "now": 13000, "in": 0, "out": 0}, {"factory": "方圆", "id": "QJ110-10C后", "name": "阀片", "first": 10000, "now": 10000, "in": 0, "out": 0}, {"factory": "方圆", "id": "QJ250T-18后", "name": "阀片", "first": 999, "now": 999, "in": 0, "out": 0}, {"factory": "方圆", "id": "QP1-125CCH", "name": "阀片A", "first": 1000, "now": 1000, "in": 0, "out": 0}, {"factory": "方圆", "id": "QP1", "name": "阀片A", "first": 0, "now": 0, "in": 0, "out": 0}, {"factory": "方圆", "id": "QP2H", "name": "阀片A", "first": 0, "now": 0, "in": 0, "out": 0}, {"factory": "方圆", "id": "QP2H", "name": "阀片B", "first": 0, "now": 0, "in": 0, "out": 0}, {"factory": "方圆", "id": "QP2Q", "name": "阀片", "first": 0, "now": 0, "in": 0, "out": 0}, {"factory": "方圆", "id": "WH125T前", "name": "阀片A", "first": 5000, "now": 5000, "in": 0, "out": 0}, {"factory": "方圆", "id": "TB50后", "name": "阀片", "first": 2000, "now": 2000, "in": 0, "out": 0}, {"factory": "方圆", "id": "2K1A后", "name": "阀片A", "first": 0, "now": 0, "in": 0, "out": 0}, {"factory": "方圆", "id": "D09A后", "name": "垫圈", "first": 8000, "now": 8000, "in": 0, "out": 0}, {"factory": "方圆", "id": "JH125后", "name": "垫圈", "first": 20000, "now": 20000, "in": 0, "out": 0}, {"factory": "方圆", "id": "JH419后", "name": "垫圈", "first": 0, "now": 0, "in": 0, "out": 0}, {"factory": "总公司", "id": "KPNM后", "name": "垫圈", "first": 40000, "now": 40000, "in": 0, "out": 0}, {"factory": "方圆", "id": "QP2后", "name": "垫圈", "first": 115000, "now": 115000, "in": 0, "out": 0}, {"factory": "方圆", "id": "QJ125F后", "name": "垫圈", "first": 3000, "now": 3000, "in": 0, "out": 0}, {"factory": "方圆", "id": "WH125T后", "name": "垫圈", "first": 50000, "now": 50000, "in": 0, "out": 0}, {"factory": "总公司", "id": "GN125后", "name": "垫圈", "first": 1000, "now": 1000, "in": 0, "out": 0}, {"factory": "方圆", "id": "JH125后", "name": "底阀弹性垫圈", "first": 10000, "now": 10000, "in": 0, "out": 0}, {"factory": "方圆", "id": "GN125后", "name": "底阀弹性垫圈", "first": 2000, "now": 2000, "in": 0, "out": 0}, {"factory": "方圆", "id": "CB125T后", "name": "鞍形弹性垫圈", "first": 10000, "now": 10000, "in": 0, "out": 0}, {"factory": "方圆", "id": "GN125后", "name": "鞍形弹性垫圈", "first": 60000, "now": 60000, "in": 0, "out": 0}, {"factory": "方圆", "id": "JH125后", "name": "鞍形弹性垫圈", "first": 20000, "now": 20000, "in": 0, "out": 0}, {"factory": "方圆", "id": "JH70后", "name": "鞍形弹性垫圈", "first": 50000, "now": 50000, "in": 0, "out": 0}, {"factory": "红卫", "id": "A6后", "name": "活塞", "first": 0, "now": 0, "in": 0, "out": 0}, {"factory": "旭发", "id": "CQ036后", "name": "活塞", "first": 4200, "now": 4200, "in": 0, "out": 0}, {"factory": "红卫", "id": "CQ036后", "name": "活塞", "first": 6000, "now": 6000, "in": 0, "out": 0}, {"factory": "红卫", "id": "CQ076后", "name": "活塞", "first": 100, "now": 100, "in": 0, "out": 0}, {"factory": "旭发", "id": "GN125后", "name": "活塞", "first": 0, "now": 0, "in": 0, "out": 0}, {"factory": "红卫", "id": "GN125后", "name": "活塞", "first": 23200, "now": 23200, "in": 0, "out": 0}, {"factory": "旭发", "id": "JH125后", "name": "活塞", "first": 22000, "now": 22000, "in": 0, "out": 0}, {"factory": "红卫", "id": "JH125后", "name": "活塞", "first": 2000, "now": 2000, "in": 0, "out": 0}, {"factory": "旭发", "id": "JH70后", "name": "活塞", "first": 0, "now": 0, "in": 0, "out": 0}, {"factory": "红卫", "id": "JH70后", "name": "活塞", "first": 25000, "now": 25000, "in": 0, "out": 0}, {"factory": "旭发", "id": "JH426后", "name": "活塞", "first": 0, "now": 0, "in": 0, "out": 0}, {"factory": "红卫", "id": "JH426后", "name": "活塞", "first": 4000, "now": 4000, "in": 0, "out": 0}, {"factory": "", "id": "K2650B", "name": "活塞", "first": 350, "now": 350, "in": 0, "out": 0}, {"factory": "红卫", "id": "KPNM后", "name": "活塞", "first": 0, "now": 0, "in": 0, "out": 0}, {"factory": "总公司KY125III", "id": "KY125III", "name": "活塞", "first": 1100, "now": 1100, "in": 0, "out": 0}, {"factory": "旭发", "id": "KYYG后", "name": "活塞", "first": 61000, "now": 61000, "in": 0, "out": 0}, {"factory": "红卫", "id": "KYYG后", "name": "活塞", "first": 20000, "now": 20000, "in": 0, "out": 0}, {"factory": "旭发", "id": "KTTA后", "name": "活塞", "first": 999, "now": 999, "in": 0, "out": 0}, {"factory": "旭发", "id": "LF100ST后", "name": "活塞", "first": 3880, "now": 3880, "in": 0, "out": 0}, {"factory": "旭发", "id": "QJ125F后", "name": "活塞", "first": 0, "now": 0, "in": 0, "out": 0}, {"factory": "红卫", "id": "QJ125F后", "name": "活塞", "first": 6700, "now": 6700, "in": 0, "out": 0}, {"factory": "旭发", "id": "MM100后", "name": "活塞", "first": 11162, "now": 11162, "in": 0, "out": 0}, {"factory": "旭发", "id": "SK150-9B后", "name": "活塞", "first": 540, "now": 540, "in": 0, "out": 0}, {"factory": "旭发", "id": "SK150-9D后", "name": "活塞", "first": 767, "now": 767, "in": 0, "out": 0}, {"factory": "旭发", "id": "C206A后", "name": "底阀座", "first": 0, "now": 0, "in": 0, "out": 0}, {"factory": "旭发", "id": "GN125后", "name": "底阀座", "first": 2800, "now": 2800, "in": 0, "out": 0}, {"factory": "红卫", "id": "CB125TH后", "name": "底阀座", "first": 2000, "now": 2000, "in": 0, "out": 0}, {"factory": "禾呈木杉", "id": "CQ075后", "name": "底阀座", "first": 28020, "now": 28020, "in": 0, "out": 0}, {"factory": "旭发", "id": "JH125后", "name": "底阀座", "first": 0, "now": 0, "in": 0, "out": 0}, {"factory": "红卫", "id": "JH125后", "name": "底阀座", "first": 8000, "now": 8000, "in": 0, "out": 0}, {"factory": "总公司", "id": "JH138后", "name": "底阀座", "first": 5000, "now": 5000, "in": 0, "out": 0}, {"factory": "", "id": "KPNM后", "name": "底阀座", "first": 5740, "now": 5740, "in": 0, "out": 0}, {"factory": "", "id": "KPH后", "name": "底阀座", "first": 0, "now": 0, "in": 0, "out": 0}, {"factory": "旭发", "id": "KY125III后", "name": "底阀座", "first": 1000, "now": 1000, "in": 0, "out": 0}, {"factory": "旭发", "id": "KYYG后", "name": "底阀座", "first": 0, "now": 0, "in": 0, "out": 0}, {"factory": "总公司", "id": "WH100T后", "name": "底阀座", "first": 14000, "now": 14000, "in": 0, "out": 0}, {"factory": "红卫", "id": "QJ125-18A后", "name": "底阀座", "first": 6000, "now": 6000, "in": 0, "out": 0}, {"factory": "旭发", "id": "JH125后", "name": "阀座", "first": 14000, "now": 14000, "in": 0, "out": 0}, {"factory": "红卫", "id": "JH125后", "name": "阀座", "first": 30000, "now": 30000, "in": 0, "out": 0}, {"factory": "红卫", "id": "JH70后", "name": "阀座", "first": 30000, "now": 30000, "in": 0, "out": 0}, {"factory": "骏亿", "id": "CB125T后", "name": "阀座A", "first": 5590, "now": 5590, "in": 0, "out": 0}, {"factory": "旭发", "id": "GN125后", "name": "阀座", "first": 0, "now": 0, "in": 0, "out": 0}, {"factory": "红卫", "id": "GN125后", "name": "阀座", "first": 20000, "now": 20000, "in": 0, "out": 0}, {"factory": "红卫", "id": "CNZ002后", "name": "导向座", "first": 0, "now": 0, "in": 0, "out": 0}, {"factory": "旭发", "id": "CNZ003后", "name": "导向座", "first": 0, "now": 0, "in": 0, "out": 0}, {"factory": "红卫", "id": "CNZ003后", "name": "导向座", "first": 2000, "now": 2000, "in": 0, "out": 0}, {"factory": "", "id": "CNZ004后", "name": "导向座", "first": 2800, "now": 2800, "in": 0, "out": 0}, {"factory": "红卫", "id": "CNZ007后", "name": "导向座", "first": 5700, "now": 5700, "in": 0, "out": 0}, {"factory": "红卫", "id": "CNZ008后", "name": "导向座", "first": 4400, "now": 4400, "in": 0, "out": 0}, {"factory": "旭发", "id": "CQ072后", "name": "导向座", "first": 25200, "now": 25200, "in": 0, "out": 0}, {"factory": "红卫", "id": "CQ072后", "name": "导向座", "first": 12400, "now": 12400, "in": 0, "out": 0}, {"factory": "旭发", "id": "GZJH125后", "name": "导向座", "first": 0, "now": 0, "in": 0, "out": 0}, {"factory": "红卫", "id": "GZXF125后", "name": "导向座", "first": 0, "now": 0, "in": 0, "out": 0}, {"factory": "红卫", "id": "XF125", "name": "导向座", "first": 14000, "now": 14000, "in": 0, "out": 0}, {"factory": "红卫", "id": "GN125后", "name": "导向座", "first": 2000, "now": 2000, "in": 0, "out": 0}, {"factory": "旭发", "id": "JH125后", "name": "导向座", "first": 0, "now": 0, "in": 0, "out": 0}, {"factory": "红卫", "id": "JH125后", "name": "导向座", "first": 9000, "now": 9000, "in": 0, "out": 0}, {"factory": "旭发", "id": "QJ125-H后", "name": "导向座", "first": 6220, "now": 6220, "in": 0, "out": 0}, {"factory": "红卫", "id": "QJ125-H后", "name": "导向座", "first": 49530, "now": 49530, "in": 0, "out": 0}, {"factory": "君威", "id": "2K1A后", "name": "拉杆", "first": 1541, "now": 1541, "in": 0, "out": 0}, {"factory": "源晟", "id": "2A8B后", "name": "拉杆", "first": 80, "now": 80, "in": 0, "out": 0}, {"factory": "源晟", "id": "AG50后", "name": "拉杆", "first": 2024, "now": 2024, "in": 0, "out": 0}, {"factory": "源晟", "id": "C001后", "name": "拉杆", "first": 4587, "now": 4587, "in": 0, "out": 0}, {"factory": "源晟", "id": "C206A后", "name": "拉杆", "first": 230, "now": 230, "in": 0, "out": 0}, {"factory": "源晟", "id": "CY80后", "name": "拉杆", "first": 1583, "now": 1583, "in": 0, "out": 0}, {"factory": "君威", "id": "CQ013后", "name": "拉杆", "first": 0, "now": 0, "in": 0, "out": 0}, {"factory": "君威", "id": "CQ049后", "name": "拉杆", "first": 0, "now": 0, "in": 0, "out": 0}, {"factory": "君威", "id": "CQ065后", "name": "拉杆", "first": 10150, "now": 10150, "in": 0, "out": 0}, {"factory": "源晟", "id": "CQ065后", "name": "拉杆", "first": 17750, "now": 17750, "in": 0, "out": 0}, {"factory": "源晟", "id": "CQ065B后", "name": "拉杆", "first": 3750, "now": 3750, "in": 0, "out": 0}, {"factory": "", "id": "CQ066后", "name": "拉杆", "first": 32650, "now": 32650, "in": 0, "out": 0}, {"factory": "君威", "id": "CQ070G后", "name": "拉杆", "first": 24300, "now": 24300, "in": 0, "out": 0}, {"factory": "君威", "id": "CQ070GB后", "name": "拉杆", "first": 1094, "now": 1094, "in": 0, "out": 0}, {"factory": "君威", "id": "CQ072后", "name": "拉杆", "first": 39250, "now": 39250, "in": 0, "out": 0}, {"factory": "源晟", "id": "CQ072后", "name": "拉杆", "first": 7750, "now": 7750, "in": 0, "out": 0}, {"factory": "君威", "id": "CQ075H后", "name": "拉杆", "first": 33837, "now": 33837, "in": 0, "out": 0}, {"factory": "君威", "id": "CQ098后", "name": "拉杆", "first": 2717, "now": 2717, "in": 0, "out": 0}, {"factory": "总公司", "id": "CQ165后", "name": "拉杆", "first": 0, "now": 0, "in": 0, "out": 0}, {"factory": "总公司", "id": "DO9A后", "name": "拉杆", "first": 0, "now": 0, "in": 0, "out": 0}, {"factory": "君威", "id": "D12A后", "name": "拉杆", "first": 2187, "now": 2187, "in": 0, "out": 0}, {"factory": "源晟", "id": "GFML后", "name": "拉杆", "first": 2022, "now": 2022, "in": 0, "out": 0}, {"factory": "君威", "id": "GN125后", "name": "拉杆", "first": 0, "now": 0, "in": 0, "out": 0}, {"factory": "君威", "id": "JD70后", "name": "拉杆", "first": 190, "now": 190, "in": 0, "out": 0}, {"factory": "君威", "id": "JH125后", "name": "拉杆", "first": 20598, "now": 20598, "in": 0, "out": 0}, {"factory": "君威", "id": "JH138后", "name": "拉杆", "first": 0, "now": 0, "in": 0, "out": 0}, {"factory": "君威", "id": "JH419后", "name": "拉杆", "first": 3050, "now": 3050, "in": 0, "out": 0}, {"factory": "源晟", "id": "JH426后", "name": "拉杆", "first": 0, "now": 0, "in": 0, "out": 0}, {"factory": "君威", "id": "JH427E后", "name": "拉杆", "first": 671, "now": 671, "in": 0, "out": 0}, {"factory": "源晟", "id": "JH70后", "name": "拉杆", "first": 4597, "now": 4597, "in": 0, "out": 0}, {"factory": "源晟", "id": "K08后", "name": "拉杆", "first": 0, "now": 0, "in": 0, "out": 0}, {"factory": "源晟", "id": "K08K后", "name": "拉杆", "first": 0, "now": 0, "in": 0, "out": 0}, {"factory": "君威", "id": "K08J后", "name": "拉杆", "first": 0, "now": 0, "in": 0, "out": 0}, {"factory": "", "id": "KY125J后", "name": "拉杆", "first": 510, "now": 510, "in": 0, "out": 0}, {"factory": "源晟", "id": "KY125III后", "name": "拉杆", "first": 1114, "now": 1114, "in": 0, "out": 0}, {"factory": "源晟", "id": "KYYL后", "name": "拉杆", "first": 107, "now": 107, "in": 0, "out": 0}, {"factory": "君威", "id": "LF125后", "name": "拉杆", "first": 7000, "now": 7000, "in": 0, "out": 0}, {"factory": "源晟", "id": "LF125后", "name": "拉杆", "first": 0, "now": 0, "in": 0, "out": 0}, {"factory": "君威", "id": "QJ125F后", "name": "拉杆", "first": 0, "now": 0, "in": 0, "out": 0}, {"factory": "源晟", "id": "QJ125F后", "name": "拉杆", "first": 3050, "now": 3050, "in": 0, "out": 0}, {"factory": "君威", "id": "QJ125-11后", "name": "拉杆", "first": 0, "now": 0, "in": 0, "out": 0}, {"factory": "源晟", "id": "QJ125-11后", "name": "拉杆", "first": 1577, "now": 1577, "in": 0, "out": 0}, {"factory": "源晟", "id": "QJ125-18A后", "name": "拉杆", "first": 1250, "now": 1250, "in": 0, "out": 0}, {"factory": "君威", "id": "QJ250-K后", "name": "拉杆", "first": 10500, "now": 10500, "in": 0, "out": 0}, {"factory": "源晟", "id": "QJ250-K后", "name": "拉杆", "first": 1000, "now": 1000, "in": 0, "out": 0}, {"factory": "源晟", "id": "QJ50QT-29B后", "name": "拉杆", "first": 5250, "now": 5250, "in": 0, "out": 0}, {"factory": "源晟", "id": "QJ200-2G后", "name": "拉杆", "first": 3825, "now": 3825, "in": 0, "out": 0}, {"factory": "君威", "id": "SD110后", "name": "拉杆", "first": 242, "now": 242, "in": 0, "out": 0}, {"factory": "源晟", "id": "SD110后", "name": "拉杆", "first": 1061, "now": 1061, "in": 0, "out": 0}, {"factory": "君威", "id": "SK150-9A后", "name": "拉杆", "first": 682, "now": 682, "in": 0, "out": 0}, {"factory": "君威", "id": "XDZ125-02后", "name": "拉杆", "first": 2650, "now": 2650, "in": 0, "out": 0}, {"factory": "", "id": "YDXA后", "name": "拉杆", "first": 5040, "now": 5040, "in": 0, "out": 0}, {"factory": "禾呈木杉", "id": "AG50后", "name": "封口垫圈(白锌）", "first": 0, "now": 0, "in": 0, "out": 0}, {"factory": "总公司", "id": "AG50后", "name": "封口垫圈(坯）", "first": 0, "now": 0, "in": 0, "out": 0}, {"factory": "总公司", "id": "AG50后", "name": "封口垫圈(白锌）", "first": 0, "now": 0, "in": 0, "out": 0}, {"factory": "胶蓝", "id": "CB125T后", "name": "封口垫圈", "first": 9000, "now": 9000, "in": 0, "out": 0}, {"factory": "禾呈木杉", "id": "CQ036后", "name": "封口垫圈（白锌）", "first": 5000, "now": 5000, "in": 0, "out": 0}, {"factory": "禾呈木杉", "id": "CQ036后", "name": "封口垫圈（镀铬）", "first": 0, "now": 0, "in": 0, "out": 0}, {"factory": "禾呈木杉", "id": "CQ036后", "name": "封口垫圈(坯）", "first": 0, "now": 0, "in": 0, "out": 0}, {"factory": "胶蓝", "id": "JH125后", "name": "封口垫圈", "first": 20000, "now": 20000, "in": 0, "out": 0}, {"factory": "胶蓝", "id": "JH138后", "name": "封口垫圈", "first": 10000, "now": 10000, "in": 0, "out": 0}, {"factory": "总公司", "id": "JH70后", "name": "封口垫圈", "first": 10000, "now": 10000, "in": 0, "out": 0}, {"factory": "胶蓝", "id": "GN125后", "name": "封口垫圈", "first": 11000, "now": 11000, "in": 0, "out": 0}, {"factory": "胶蓝", "id": "KCS125后", "name": "封口垫圈", "first": 35000, "now": 35000, "in": 0, "out": 0}, {"factory": "", "id": "KWKF后", "name": "封口垫圈", "first": 0, "now": 0, "in": 0, "out": 0}, {"factory": "", "id": "YDXA后", "name": "封口垫圈", "first": 1600, "now": 1600, "in": 0, "out": 0}, {"factory": "胶蓝", "id": "AG50后", "name": "油封", "first": 0, "now": 0, "in": 0, "out": 0}, {"factory": "胶蓝茂林", "id": "CB125T后", "name": "油封", "first": 5860, "now": 5860, "in": 0, "out": 0}, {"factory": "胶蓝茂林", "id": "CQ072后", "name": "油封", "first": 54000, "now": 54000, "in": 0, "out": 0}, {"factory": "胶蓝", "id": "GN125后", "name": "油封", "first": 43000, "now": 43000, "in": 0, "out": 0}, {"factory": "胶蓝", "id": "JH125后", "name": "油封", "first": 15000, "now": 15000, "in": 0, "out": 0}, {"factory": "胶蓝", "id": "JH138后", "name": "油封", "first": 10000, "now": 10000, "in": 0, "out": 0}, {"factory": "胶蓝", "id": "JH70后", "name": "油封", "first": 3000, "now": 3000, "in": 0, "out": 0}, {"factory": "胶蓝", "id": "XDZ125T-5后", "name": "油封", "first": 26000, "now": 26000, "in": 0, "out": 0}, {"factory": "胶蓝", "id": "CN03H后", "name": "橡胶垫圈", "first": 12000, "now": 12000, "in": 0, "out": 0}, {"factory": "耀邦", "id": "M6", "name": "螺母（彩）", "first": 99000, "now": 99000, "in": 0, "out": 0}, {"factory": "外购", "id": "￠7", "name": "开口挡圈", "first": 16000, "now": 16000, "in": 0, "out": 0}, {"factory": "外购", "id": "￠9", "name": "开口挡圈", "first": 0, "now": 0, "in": 0, "out": 0}, {"factory": "外购", "id": "Φ16", "name": "孔用挡圈", "first": 4000, "now": 4000, "in": 0, "out": 0}, {"factory": "外购", "id": "Φ17", "name": "孔用挡圈", "first": 17000, "now": 17000, "in": 0, "out": 0}, {"factory": "外购", "id": "Φ18", "name": "孔用挡圈", "first": 6000, "now": 6000, "in": 0, "out": 0}, {"factory": "亮友", "id": "2A8B后", "name": "内弹簧", "first": 0, "now": 0, "in": 0, "out": 0}, {"factory": "亮友", "id": "CB125T后", "name": "内弹簧", "first": 3100, "now": 3100, "in": 0, "out": 0}, {"factory": "亮友", "id": "CY80后", "name": "内弹簧", "first": 182, "now": 182, "in": 0, "out": 0}, {"factory": "四源", "id": "CY80后", "name": "内弹簧", "first": 23309, "now": 23309, "in": 0, "out": 0}, {"factory": "四源", "id": "CQ072后", "name": "内弹簧", "first": 47730, "now": 47730, "in": 0, "out": 0}, {"factory": "亮友", "id": "CQ072后", "name": "内弹簧", "first": 0, "now": 0, "in": 0, "out": 0}, {"factory": "亮友", "id": "JH125后", "name": "内弹簧", "first": 11550, "now": 11550, "in": 0, "out": 0}, {"factory": "亮友", "id": "JH70", "name": "内弹簧", "first": 9490, "now": 9490, "in": 0, "out": 0}, {"factory": "亮友", "id": "GN125后", "name": "内弹簧", "first": 6000, "now": 6000, "in": 0, "out": 0}, {"factory": "亮友", "id": "QJ125-18A", "name": "内弹簧", "first": 59965, "now": 59965, "in": 0, "out": 0}, {"factory": "亮友", "id": "LF100STA", "name": "后锥弹簧", "first": 3890, "now": 3890, "in": 0, "out": 0}, {"factory": "渝蓝", "id": "CB125T后", "name": "活塞环", "first": 6930, "now": 6930, "in": 0, "out": 0}, {"factory": "渝蓝", "id": "GN125后", "name": "活塞环", "first": 58000, "now": 58000, "in": 0, "out": 0}, {"factory": "渝蓝", "id": "JH125", "name": "活塞环", "first": 58000, "now": 58000, "in": 0, "out": 0}, {"factory": "渝蓝", "id": "JH426后", "name": "活塞环", "first": 8000, "now": 8000, "in": 0, "out": 0}, {"factory": "渝蓝", "id": "JH70后", "name": "活塞环", "first": 42000, "now": 42000, "in": 0, "out": 0}, {"factory": "渝蓝", "id": "KWKF后", "name": "活塞环", "first": 0, "now": 0, "in": 0, "out": 0}]}